l2s/__init__.py
l2s/_intermediate_format.py
l2s/_simple_sim.py
l2s/api.py
l2s-1.1.dist-info/WHEEL
l2s-1.1.dist-info/METADATA
l2s-1.1.dist-info/RECORD
