Metadata-Version: 2.1
Name: l2s
Version: 1.1
Summary: CRI User Software
Author: Justin Frank & Abhinav Uppal
Requires-Python: >=3.9,<3.11
Classifier: Programming Language :: Python :: 3
Classifier: Programming Language :: Python :: 3.10
Classifier: Programming Language :: Python :: 3.9
Requires-Dist: PyYAML (>=6.0,<7.0)
Requires-Dist: bidict (>=0.22.0,<0.23.0)
Requires-Dist: cri-simulations (>=1.1,<2.0)
Requires-Dist: matplotlib (>=3.5.1,<4.0.0)
Requires-Dist: numba (>=0.55.1,<0.56.0)
Requires-Dist: numpy (>=1.18)
